{
  "autoChart": {
    "chartType": "auto",
    "dataset": {
      "columns": [
        {
          "id": "week",
          "type": "string"
        },
        {
          "id": "th",
          "type": "number",
          "label": "2026",
          "color": "#006D88"
        },
        {
          "id": "ck",
          "type": "number",
          "label": "2025",
          "color": "#9AA0A6"
        },
        {
          "id": "db",
          "type": "number",
          "label": "KH 2026",
          "color": "#D3AC2B"
        },
        {
          "id": "uth",
          "type": "number",
          "label": "Dự báo",
          "color": "#006D88"
        }
      ],
      "rows": [
        [
          "W1",
          37.3,
          35.2,
          39.5,
          null
        ],
        [
          "W2",
          37.3,
          35.2,
          39.5,
          null
        ],
        [
          "W3",
          37.3,
          35.2,
          39.5,
          null
        ],
        [
          "W4",
          37.3,
          35.2,
          39.5,
          null
        ],
        [
          "W5",
          37.3,
          35.2,
          39.5,
          null
        ],
        [
          "W6",
          41.8,
          43.0,
          50.4,
          null
        ],
        [
          "W7",
          41.8,
          43.0,
          50.4,
          null
        ],
        [
          "W8",
          41.8,
          43.0,
          50.4,
          null
        ],
        [
          "W9",
          41.8,
          43.0,
          50.4,
          null
        ],
        [
          "W10",
          43.9,
          45.0,
          49.4,
          null
        ],
        [
          "W11",
          43.9,
          45.0,
          49.4,
          null
        ],
        [
          "W12",
          43.9,
          45.0,
          49.4,
          null
        ],
        [
          "W13",
          43.9,
          45.0,
          49.4,
          null
        ],
        [
          "W14",
          34.2,
          36.5,
          39.0,
          null
        ],
        [
          "W15",
          34.2,
          36.5,
          39.0,
          null
        ],
        [
          "W16",
          34.2,
          36.5,
          39.0,
          null
        ],
        [
          "W17",
          34.2,
          36.5,
          39.0,
          null
        ],
        [
          "W18",
          34.2,
          36.5,
          39.0,
          null
        ],
        [
          "W19",
          38.9,
          43.9,
          48.1,
          null
        ],
        [
          "W20",
          38.9,
          43.9,
          48.1,
          null
        ],
        [
          "W21",
          38.9,
          43.9,
          48.1,
          null
        ],
        [
          "W22",
          38.9,
          43.9,
          48.1,
          null
        ],
        [
          "W23",
          41.4,
          42.4,
          47.5,
          null
        ],
        [
          "W24",
          41.4,
          42.4,
          47.5,
          null
        ],
        [
          "W25",
          41.4,
          42.4,
          47.5,
          null
        ],
        [
          "W26",
          41.4,
          42.4,
          47.5,
          null
        ],
        [
          "W27",
          32.6,
          34.2,
          37.2,
          null
        ],
        [
          "W28",
          32.6,
          34.2,
          37.2,
          null
        ],
        [
          "W29",
          32.6,
          34.2,
          37.2,
          null
        ],
        [
          "W30",
          32.6,
          34.2,
          37.2,
          null
        ],
        [
          "W31",
          null,
          34.2,
          37.2,
          null
        ],
        [
          "W32",
          null,
          41.1,
          47.2,
          41.0
        ],
        [
          "W33",
          null,
          41.1,
          47.2,
          41.0
        ],
        [
          "W34",
          null,
          41.1,
          47.2,
          41.0
        ],
        [
          "W35",
          null,
          41.1,
          47.2,
          41.0
        ],
        [
          "W36",
          null,
          41.6,
          47.6,
          41.4
        ],
        [
          "W37",
          null,
          41.6,
          47.6,
          41.4
        ],
        [
          "W38",
          null,
          41.6,
          47.6,
          41.4
        ],
        [
          "W39",
          null,
          41.6,
          47.6,
          41.4
        ],
        [
          "W40",
          null,
          31.8,
          37.0,
          32.2
        ],
        [
          "W41",
          null,
          31.8,
          37.0,
          32.2
        ],
        [
          "W42",
          null,
          31.8,
          37.0,
          32.2
        ],
        [
          "W43",
          null,
          31.8,
          37.0,
          32.2
        ],
        [
          "W44",
          null,
          31.8,
          37.0,
          32.2
        ],
        [
          "W45",
          null,
          38.6,
          44.9,
          39.0
        ],
        [
          "W46",
          null,
          38.6,
          44.9,
          39.0
        ],
        [
          "W47",
          null,
          38.6,
          44.9,
          39.0
        ],
        [
          "W48",
          null,
          38.6,
          44.9,
          39.0
        ],
        [
          "W49",
          null,
          40.0,
          45.2,
          39.4
        ],
        [
          "W50",
          null,
          40.0,
          45.2,
          39.4
        ],
        [
          "W51",
          null,
          40.0,
          45.2,
          39.4
        ],
        [
          "W52",
          null,
          40.0,
          45.2,
          39.4
        ]
      ]
    },
    "views": [
      {
        "id": "main",
        "chartType": "auto",
        "xField": "week",
        "series": [
          {
            "field": "th",
            "chartType": "line"
          },
          {
            "field": "ck",
            "chartType": "line"
          },
          {
            "field": "db",
            "chartType": "line",
            "lineStyle": "dashed"
          },
          {
            "field": "uth",
            "chartType": "bar"
          }
        ]
      }
    ]
  },
  "metadata": {
    "chartType": "line",
    "pattern": "fluctuation",
    "unit": "VND/ghế.km",
    "description": "CASK Non Fuel - Chi phí phi nhiên liệu - nội địa",
    "forecastStartIndex": 31
  }
}