{
  "autoChart": {
    "chartType": "auto",
    "dataset": {
      "columns": [
        {
          "id": "week",
          "type": "string"
        },
        {
          "id": "th",
          "type": "number",
          "label": "2026",
          "color": "#006D88"
        },
        {
          "id": "ck",
          "type": "number",
          "label": "2025",
          "color": "#9AA0A6"
        },
        {
          "id": "db",
          "type": "number",
          "label": "KH 2026",
          "color": "#D3AC2B"
        },
        {
          "id": "uth",
          "type": "number",
          "label": "Dự báo",
          "color": "#006D88"
        }
      ],
      "rows": [
        [
          "W1",
          9.1,
          10.1,
          13.6,
          null
        ],
        [
          "W2",
          9.1,
          10.1,
          13.6,
          null
        ],
        [
          "W3",
          9.1,
          10.1,
          13.6,
          null
        ],
        [
          "W4",
          9.1,
          10.1,
          13.6,
          null
        ],
        [
          "W5",
          9.1,
          10.1,
          13.6,
          null
        ],
        [
          "W6",
          12.2,
          12.1,
          17.1,
          null
        ],
        [
          "W7",
          12.2,
          12.1,
          17.1,
          null
        ],
        [
          "W8",
          12.2,
          12.1,
          17.1,
          null
        ],
        [
          "W9",
          12.2,
          12.1,
          17.1,
          null
        ],
        [
          "W10",
          12.3,
          12.2,
          17.4,
          null
        ],
        [
          "W11",
          12.3,
          12.2,
          17.4,
          null
        ],
        [
          "W12",
          12.3,
          12.2,
          17.4,
          null
        ],
        [
          "W13",
          12.3,
          12.2,
          17.4,
          null
        ],
        [
          "W14",
          9.2,
          10.0,
          13.5,
          null
        ],
        [
          "W15",
          9.2,
          10.0,
          13.5,
          null
        ],
        [
          "W16",
          9.2,
          10.0,
          13.5,
          null
        ],
        [
          "W17",
          9.2,
          10.0,
          13.5,
          null
        ],
        [
          "W18",
          9.2,
          10.0,
          13.5,
          null
        ],
        [
          "W19",
          11.5,
          11.7,
          16.6,
          null
        ],
        [
          "W20",
          11.5,
          11.7,
          16.6,
          null
        ],
        [
          "W21",
          11.5,
          11.7,
          16.6,
          null
        ],
        [
          "W22",
          11.5,
          11.7,
          16.6,
          null
        ],
        [
          "W23",
          11.5,
          12.1,
          16.8,
          null
        ],
        [
          "W24",
          11.5,
          12.1,
          16.8,
          null
        ],
        [
          "W25",
          11.5,
          12.1,
          16.8,
          null
        ],
        [
          "W26",
          11.5,
          12.1,
          16.8,
          null
        ],
        [
          "W27",
          9.0,
          9.2,
          13.6,
          null
        ],
        [
          "W28",
          9.0,
          9.2,
          13.6,
          null
        ],
        [
          "W29",
          9.0,
          9.2,
          13.6,
          null
        ],
        [
          "W30",
          9.0,
          9.2,
          13.6,
          null
        ],
        [
          "W31",
          null,
          9.2,
          13.6,
          null
        ],
        [
          "W32",
          null,
          11.4,
          16.9,
          14.4
        ],
        [
          "W33",
          null,
          11.4,
          16.9,
          14.4
        ],
        [
          "W34",
          null,
          11.4,
          16.9,
          14.4
        ],
        [
          "W35",
          null,
          11.4,
          16.9,
          14.4
        ],
        [
          "W36",
          null,
          11.9,
          16.8,
          14.3
        ],
        [
          "W37",
          null,
          11.9,
          16.8,
          14.3
        ],
        [
          "W38",
          null,
          11.9,
          16.8,
          14.3
        ],
        [
          "W39",
          null,
          11.9,
          16.8,
          14.3
        ],
        [
          "W40",
          null,
          9.1,
          13.5,
          11.4
        ],
        [
          "W41",
          null,
          9.1,
          13.5,
          11.4
        ],
        [
          "W42",
          null,
          9.1,
          13.5,
          11.4
        ],
        [
          "W43",
          null,
          9.1,
          13.5,
          11.4
        ],
        [
          "W44",
          null,
          9.1,
          13.5,
          11.4
        ],
        [
          "W45",
          null,
          11.2,
          16.1,
          13.7
        ],
        [
          "W46",
          null,
          11.2,
          16.1,
          13.7
        ],
        [
          "W47",
          null,
          11.2,
          16.1,
          13.7
        ],
        [
          "W48",
          null,
          11.2,
          16.1,
          13.7
        ],
        [
          "W49",
          null,
          11.1,
          16.1,
          13.7
        ],
        [
          "W50",
          null,
          11.1,
          16.1,
          13.7
        ],
        [
          "W51",
          null,
          11.1,
          16.1,
          13.7
        ],
        [
          "W52",
          null,
          11.1,
          16.1,
          13.7
        ]
      ]
    },
    "views": [
      {
        "id": "main",
        "chartType": "auto",
        "xField": "week",
        "series": [
          {
            "field": "th",
            "chartType": "line"
          },
          {
            "field": "ck",
            "chartType": "line"
          },
          {
            "field": "db",
            "chartType": "line"
          },
          {
            "field": "uth",
            "chartType": "bar"
          }
        ]
      }
    ]
  },
  "metadata": {
    "chartType": "line",
    "pattern": "downWave",
    "description": "int int clmv",
    "forecastStartIndex": 31
  }
}