{
  "autoChart": {
    "chartType": "auto",
    "dataset": {
      "columns": [
        {
          "id": "month",
          "type": "string"
        },
        {
          "id": "th",
          "type": "number",
          "label": "Thực hiện 2026",
          "color": "#006D88"
        },
        {
          "id": "ck",
          "type": "number",
          "label": "Cùng kỳ 2025",
          "color": "#9AA0A6"
        },
        {
          "id": "db",
          "type": "number",
          "label": "Kế hoạch 2026",
          "color": "#D3AC2B"
        }
      ],
      "rows": [
        [
          "10/7",
          1.67,
          1.26,
          1.61
        ],
        [
          "11/7",
          1.42,
          1.23,
          1.64
        ],
        [
          "12/7",
          1.55,
          1.37,
          1.61
        ],
        [
          "13/7",
          1.54,
          1.47,
          1.79
        ],
        [
          "14/7",
          1.44,
          1.24,
          1.62
        ],
        [
          "15/7",
          1.67,
          1.47,
          1.6
        ],
        [
          "16/7",
          1.67,
          1.43,
          1.7
        ],
        [
          "17/7",
          1.5,
          1.42,
          1.79
        ],
        [
          "18/7",
          1.4,
          1.24,
          1.53
        ],
        [
          "19/7",
          1.68,
          1.41,
          1.76
        ],
        [
          "20/7",
          1.59,
          1.32,
          1.56
        ],
        [
          "21/7",
          1.6,
          1.23,
          1.62
        ],
        [
          "22/7",
          1.69,
          1.23,
          1.65
        ],
        [
          "23/7",
          1.53,
          1.29,
          1.62
        ]
      ]
    },
    "views": [
      {
        "id": "main",
        "chartType": "auto",
        "xField": "month",
        "series": [
          {
            "field": "th",
            "chartType": "line"
          },
          {
            "field": "ck",
            "chartType": "line"
          },
          {
            "field": "db",
            "chartType": "line",
            "lineStyle": "dashed"
          }
        ]
      }
    ]
  },
  "metadata": {
    "chartType": "line",
    "pattern": "downWave",
    "unit": "tỷ VND",
    "description": "PL - Lợi nhuận - nội địa",
    "forecastStartIndex": 8
  }
}