{
  "autoChart": {
    "chartType": "auto",
    "dataset": {
      "columns": [
        {
          "id": "month",
          "type": "string"
        },
        {
          "id": "ck",
          "type": "number",
          "label": "Cùng kỳ 2026",
          "color": "#9AA0A6"
        },
        {
          "id": "db",
          "type": "number",
          "label": "Kế hoạch 2027",
          "color": "#D3AC2B"
        },
        {
          "id": "th",
          "type": "number",
          "label": "Thực hiện 2027",
          "color": "#006D88"
        },
        {
          "id": "uth",
          "type": "number",
          "label": "Dự báo",
          "color": "#006D88"
        }
      ],
      "rows": [
        [
          "T1",
          199.9,
          239.7,
          189,
          null
        ],
        [
          "T2",
          200.6,
          239.4,
          168.4,
          null
        ],
        [
          "T3",
          190.2,
          212.9,
          174,
          null
        ],
        [
          "T4",
          163.9,
          215,
          154.1,
          null
        ],
        [
          "T5",
          179.8,
          263.1,
          181,
          null
        ],
        [
          "T6",
          216.1,
          245.5,
          206.1,
          null
        ],
        [
          "T7",
          218.7,
          237.4,
          192.2,
          null
        ],
        [
          "T8",
          194.4,
          183.5,
          null,
          156.0
        ],
        [
          "T9",
          176.2,
          176.2,
          null,
          149.8
        ],
        [
          "T10",
          156.7,
          188.7,
          null,
          160.4
        ],
        [
          "T11",
          177.8,
          231.1,
          null,
          196.4
        ],
        [
          "T12",
          194.3,
          239,
          null,
          203.2
        ]
      ]
    },
    "views": [
      {
        "id": "main",
        "chartType": "auto",
        "xField": "month",
        "series": [
          {
            "field": "ck",
            "chartType": "line"
          },
          {
            "field": "db",
            "chartType": "line"
          },
          {
            "field": "th",
            "chartType": "line"
          },
          {
            "field": "uth",
            "chartType": "bar"
          }
        ]
      }
    ]
  },
  "metadata": {
    "chartType": "line",
    "pattern": "fluctuation",
    "description": "int/rask/cf_network_int_b_int_rask_au_us.json",
    "forecastStartIndex": 8,
    "metric": "rask"
  }
}
