{
  "autoChart": {
    "chartType": "treemap",
    "dataset": {
      "columns": [
        {
          "id": "name",
          "type": "string"
        },
        {
          "id": "value",
          "type": "number"
        },
        {
          "id": "parent",
          "type": "string"
        },
        {
          "id": "color",
          "type": "string"
        }
      ],
      "rows": [
        [
          "W1",
          21.95,
          null,
          null
        ],
        [
          "W2",
          23.54,
          null,
          null
        ],
        [
          "W3",
          22.38,
          null,
          null
        ],
        [
          "W4",
          22.27,
          null,
          null
        ],
        [
          "W5",
          11504.6,
          null,
          null
        ],
        [
          "W6",
          11793.33,
          null,
          null
        ],
        [
          "W7",
          11357.73,
          null,
          null
        ],
        [
          "W8",
          11269.81,
          null,
          null
        ],
        [
          "W9",
          2644.34,
          null,
          null
        ],
        [
          "W10",
          2470.06,
          null,
          null
        ],
        [
          "W11",
          2469.68,
          null,
          null
        ],
        [
          "W12",
          2449.92,
          null,
          null
        ],
        [
          "W13",
          2609.64,
          null,
          null
        ],
        [
          "W14",
          2463.74,
          null,
          null
        ],
        [
          "W15",
          2670.8,
          null,
          null
        ],
        [
          "W16",
          2636.59,
          null,
          null
        ],
        [
          "W17",
          2529.53,
          null,
          null
        ],
        [
          "W18",
          1900.14,
          null,
          null
        ],
        [
          "W19",
          1900.65,
          null,
          null
        ],
        [
          "W20",
          1970.5,
          null,
          null
        ],
        [
          "W21",
          1824.74,
          null,
          null
        ],
        [
          "W22",
          995.74,
          null,
          null
        ],
        [
          "W23",
          1028.93,
          null,
          null
        ],
        [
          "W24",
          1006.25,
          null,
          null
        ],
        [
          "W25",
          1030.12,
          null,
          null
        ],
        [
          "W26",
          1052.58,
          null,
          null
        ],
        [
          "W27",
          1160.66,
          null,
          null
        ],
        [
          "W28",
          1229.6,
          null,
          null
        ],
        [
          "W29",
          1143.83,
          null,
          null
        ],
        [
          "W30",
          1180.55,
          null,
          null
        ],
        [
          "W31",
          1172.01,
          null,
          null
        ],
        [
          "W32",
          1151.35,
          null,
          null
        ],
        [
          "W33",
          1150.15,
          null,
          null
        ],
        [
          "W34",
          1157.95,
          null,
          null
        ],
        [
          "W35",
          10882.02,
          null,
          null
        ],
        [
          "W36",
          11616.42,
          null,
          null
        ],
        [
          "W37",
          11463.29,
          null,
          null
        ],
        [
          "W38",
          11335.76,
          null,
          null
        ],
        [
          "W39",
          11708.61,
          null,
          null
        ],
        [
          "W40",
          3761.48,
          null,
          null
        ],
        [
          "W41",
          3651.63,
          null,
          null
        ],
        [
          "W42",
          3811.99,
          null,
          null
        ],
        [
          "W43",
          3754.42,
          null,
          null
        ],
        [
          "W44",
          3103.43,
          null,
          null
        ],
        [
          "W45",
          3096.12,
          null,
          null
        ],
        [
          "W46",
          3327.77,
          null,
          null
        ],
        [
          "W47",
          3190.73,
          null,
          null
        ],
        [
          "W48",
          1230.32,
          null,
          null
        ],
        [
          "W49",
          1182.55,
          null,
          null
        ],
        [
          "W50",
          1236.36,
          null,
          null
        ],
        [
          "W51",
          1236.6,
          null,
          null
        ],
        [
          "W52",
          1159.91,
          null,
          null
        ]
      ]
    },
    "views": [
      {
        "id": "main",
        "chartType": "treemap",
        "series": []
      }
    ]
  },
  "metadata": {
    "chartType": "line",
    "pattern": "stable",
    "unit": "tỷ tấn.km",
    "description": "RTK - Luân chuyển hàng hóa"
  }
}