{
  "filterViews": [
    {
      "label": "Area",
      "table": {
        "columns": [
          {
            "id": "level",
            "label": "TÊN MỨC",
            "type": "chip",
            "align": "left"
          },
          {
            "id": "th",
            "label": "TH",
            "type": "number",
            "align": "right",
            "decimals": 1
          },
          {
            "id": "ck",
            "label": "CK",
            "type": "number",
            "align": "right",
            "decimals": 1
          },
          {
            "id": "kh",
            "label": "KH",
            "type": "number",
            "align": "right",
            "decimals": 1
          },
          {
            "id": "pct_ck",
            "label": "% CK",
            "type": "trend",
            "align": "right"
          },
          {
            "id": "pct_kh",
            "label": "% KH",
            "type": "trend",
            "align": "right"
          },
          {
            "id": "unit",
            "label": "Đơn vị",
            "type": "text",
            "align": "left"
          }
        ],
        "rows": [
          {
            "id": "clmv",
            "cells": {
              "level": {
                "label": "CLMV",
                "color": "blue"
              },
              "th": 1122.1,
              "ck": 1059.8,
              "kh": 1089.9,
              "pct_ck": {
                "direction": "up",
                "label": "+5,9%",
                "color": "green"
              },
              "pct_kh": {
                "direction": "up",
                "label": "+3,0%",
                "color": "green"
              },
              "unit": "VND/ghế/km"
            },
            "depth": 0
          },
          {
            "id": "nea",
            "cells": {
              "level": {
                "label": "NEA",
                "color": "green"
              },
              "th": 1037.9,
              "ck": 978.7,
              "kh": 1006.4,
              "pct_ck": {
                "direction": "up",
                "label": "+6,0%",
                "color": "green"
              },
              "pct_kh": {
                "direction": "up",
                "label": "+3,1%",
                "color": "green"
              },
              "unit": "VND/ghế/km"
            },
            "depth": 0
          },
          {
            "id": "mid",
            "cells": {
              "level": {
                "label": "MID",
                "color": "default"
              },
              "th": 952.6,
              "ck": 898,
              "kh": 924.2,
              "pct_ck": {
                "direction": "up",
                "label": "+6,1%",
                "color": "green"
              },
              "pct_kh": {
                "direction": "up",
                "label": "+3,1%",
                "color": "green"
              },
              "unit": "VND/ghế/km"
            },
            "depth": 0
          },
          {
            "id": "noa",
            "cells": {
              "level": {
                "label": "NOA",
                "color": "yellow"
              },
              "th": 868.1,
              "ck": 819,
              "kh": 845,
              "pct_ck": {
                "direction": "up",
                "label": "+6,0%",
                "color": "green"
              },
              "pct_kh": {
                "direction": "up",
                "label": "+2,7%",
                "color": "green"
              },
              "unit": "VND/ghế/km"
            },
            "depth": 0
          },
          {
            "id": "swp",
            "cells": {
              "level": {
                "label": "SWP",
                "color": "blue"
              },
              "th": 786,
              "ck": 743.2,
              "kh": 769.5,
              "pct_ck": {
                "direction": "up",
                "label": "+5,8%",
                "color": "green"
              },
              "pct_kh": {
                "direction": "up",
                "label": "+2,1%",
                "color": "green"
              },
              "unit": "VND/ghế/km"
            },
            "depth": 0
          },
          {
            "id": "sea",
            "cells": {
              "level": {
                "label": "SEA",
                "color": "green"
              },
              "th": 707.4,
              "ck": 671.4,
              "kh": 697.4,
              "pct_ck": {
                "direction": "up",
                "label": "+5,4%",
                "color": "green"
              },
              "pct_kh": {
                "direction": "up",
                "label": "+1,4%",
                "color": "green"
              },
              "unit": "VND/ghế/km"
            },
            "depth": 0
          },
          {
            "id": "eur",
            "cells": {
              "level": {
                "label": "EUR",
                "color": "default"
              },
              "th": 632.4,
              "ck": 602.6,
              "kh": 627.8,
              "pct_ck": {
                "direction": "up",
                "label": "+4,9%",
                "color": "green"
              },
              "pct_kh": {
                "direction": "up",
                "label": "+0,7%",
                "color": "green"
              },
              "unit": "VND/ghế/km"
            },
            "depth": 0
          },
          {
            "id": "sas",
            "cells": {
              "level": {
                "label": "SAS",
                "color": "yellow"
              },
              "th": 560.4,
              "ck": 535.9,
              "kh": 559.1,
              "pct_ck": {
                "direction": "up",
                "label": "+4,6%",
                "color": "green"
              },
              "pct_kh": {
                "direction": "up",
                "label": "+0,2%",
                "color": "green"
              },
              "unit": "VND/ghế/km"
            },
            "depth": 0
          },
          {
            "id": "hansgn",
            "cells": {
              "level": {
                "label": "HANSGN",
                "color": "blue"
              },
              "th": 1101.2,
              "ck": 1048.9,
              "kh": 1087.9,
              "pct_ck": {
                "direction": "up",
                "label": "+5,0%",
                "color": "green"
              },
              "pct_kh": {
                "direction": "up",
                "label": "+1,2%",
                "color": "green"
              },
              "unit": "VND/ghế/km"
            },
            "depth": 0
          },
          {
            "id": "handad",
            "cells": {
              "level": {
                "label": "HANDAD",
                "color": "green"
              },
              "th": 1030.5,
              "ck": 981.2,
              "kh": 1015.9,
              "pct_ck": {
                "direction": "up",
                "label": "+5,0%",
                "color": "green"
              },
              "pct_kh": {
                "direction": "up",
                "label": "+1,4%",
                "color": "green"
              },
              "unit": "VND/ghế/km"
            },
            "depth": 0
          },
          {
            "id": "sgndad",
            "cells": {
              "level": {
                "label": "SGNDAD",
                "color": "default"
              },
              "th": 957.9,
              "ck": 910.3,
              "kh": 940.1,
              "pct_ck": {
                "direction": "up",
                "label": "+5,2%",
                "color": "green"
              },
              "pct_kh": {
                "direction": "up",
                "label": "+1,9%",
                "color": "green"
              },
              "unit": "VND/ghế/km"
            },
            "depth": 0
          },
          {
            "id": "trục_lẻ",
            "cells": {
              "level": {
                "label": "Trục lẻ",
                "color": "yellow"
              },
              "th": 881.9,
              "ck": 835.8,
              "kh": 860.7,
              "pct_ck": {
                "direction": "up",
                "label": "+5,5%",
                "color": "green"
              },
              "pct_kh": {
                "direction": "up",
                "label": "+2,5%",
                "color": "green"
              },
              "unit": "VND/ghế/km"
            },
            "depth": 0
          },
          {
            "id": "du_lịch",
            "cells": {
              "level": {
                "label": "Du lịch",
                "color": "blue"
              },
              "th": 802.3,
              "ck": 758,
              "kh": 778.4,
              "pct_ck": {
                "direction": "up",
                "label": "+5,8%",
                "color": "green"
              },
              "pct_kh": {
                "direction": "up",
                "label": "+3,1%",
                "color": "green"
              },
              "unit": "VND/ghế/km"
            },
            "depth": 0
          },
          {
            "id": "dịa_phương",
            "cells": {
              "level": {
                "label": "Địa phương",
                "color": "green"
              },
              "th": 0.1,
              "ck": 0.1,
              "kh": 0.1,
              "pct_ck": {
                "direction": "up",
                "label": "+0,0%",
                "color": "green"
              },
              "pct_kh": {
                "direction": "up",
                "label": "+0,0%",
                "color": "green"
              },
              "unit": "VND/ghế/km"
            },
            "depth": 0
          }
        ],
        "maxHeight": 385,
        "minHeight": 385
      },
      "aiInsight": {
        "text": "CASK toàn mạng cho thấy áp lực chi phí theo mức; cần kiểm soát chi phí đơn vị ghế.km.",
        "severity": "warn",
        "status": 1
      },
      "title": "Chi tiết CASK theo Area"
    },
    {
      "label": "Country",
      "table": {
        "columns": [
          {
            "id": "level",
            "label": "TÊN MỨC",
            "type": "chip",
            "align": "left"
          },
          {
            "id": "th",
            "label": "TH",
            "type": "number",
            "align": "right",
            "decimals": 1
          },
          {
            "id": "ck",
            "label": "CK",
            "type": "number",
            "align": "right",
            "decimals": 1
          },
          {
            "id": "kh",
            "label": "KH",
            "type": "number",
            "align": "right",
            "decimals": 1
          },
          {
            "id": "pct_ck",
            "label": "% CK",
            "type": "trend",
            "align": "right"
          },
          {
            "id": "pct_kh",
            "label": "% KH",
            "type": "trend",
            "align": "right"
          },
          {
            "id": "unit",
            "label": "Đơn vị",
            "type": "text",
            "align": "left"
          }
        ],
        "rows": [
          {
            "id": "clmv",
            "cells": {
              "level": {
                "label": "CLMV",
                "color": "blue"
              },
              "th": 1122.1,
              "ck": 1059.8,
              "kh": 1089.9,
              "pct_ck": {
                "direction": "up",
                "label": "+5,9%",
                "color": "green"
              },
              "pct_kh": {
                "direction": "up",
                "label": "+3,0%",
                "color": "green"
              },
              "unit": "VND/ghế/km"
            },
            "depth": 0
          },
          {
            "id": "vietnam",
            "cells": {
              "level": {
                "label": "Vietnam",
                "color": "blue"
              },
              "th": 810.4,
              "ck": 764.2,
              "kh": 788.4,
              "pct_ck": {
                "direction": "up",
                "label": "+6,0%",
                "color": "green"
              },
              "pct_kh": {
                "direction": "up",
                "label": "+2,8%",
                "color": "green"
              },
              "unit": "VND/ghế/km"
            },
            "depth": 1
          },
          {
            "id": "nea",
            "cells": {
              "level": {
                "label": "NEA",
                "color": "green"
              },
              "th": 1037.9,
              "ck": 978.7,
              "kh": 1006.4,
              "pct_ck": {
                "direction": "up",
                "label": "+6,0%",
                "color": "green"
              },
              "pct_kh": {
                "direction": "up",
                "label": "+3,1%",
                "color": "green"
              },
              "unit": "VND/ghế/km"
            },
            "depth": 0
          },
          {
            "id": "korea",
            "cells": {
              "level": {
                "label": "Korea",
                "color": "green"
              },
              "th": 748.7,
              "ck": 708,
              "kh": 733,
              "pct_ck": {
                "direction": "up",
                "label": "+5,7%",
                "color": "green"
              },
              "pct_kh": {
                "direction": "up",
                "label": "+2,1%",
                "color": "green"
              },
              "unit": "VND/ghế/km"
            },
            "depth": 1
          },
          {
            "id": "japan",
            "cells": {
              "level": {
                "label": "Japan",
                "color": "default"
              },
              "th": 690.4,
              "ck": 655.3,
              "kh": 680.8,
              "pct_ck": {
                "direction": "up",
                "label": "+5,4%",
                "color": "green"
              },
              "pct_kh": {
                "direction": "up",
                "label": "+1,4%",
                "color": "green"
              },
              "unit": "VND/ghế/km"
            },
            "depth": 1
          },
          {
            "id": "mid",
            "cells": {
              "level": {
                "label": "MID",
                "color": "default"
              },
              "th": 952.6,
              "ck": 898,
              "kh": 924.2,
              "pct_ck": {
                "direction": "up",
                "label": "+6,1%",
                "color": "green"
              },
              "pct_kh": {
                "direction": "up",
                "label": "+3,1%",
                "color": "green"
              },
              "unit": "VND/ghế/km"
            },
            "depth": 0
          },
          {
            "id": "noa",
            "cells": {
              "level": {
                "label": "NOA",
                "color": "yellow"
              },
              "th": 868.1,
              "ck": 819,
              "kh": 845,
              "pct_ck": {
                "direction": "up",
                "label": "+6,0%",
                "color": "green"
              },
              "pct_kh": {
                "direction": "up",
                "label": "+2,7%",
                "color": "green"
              },
              "unit": "VND/ghế/km"
            },
            "depth": 0
          },
          {
            "id": "swp",
            "cells": {
              "level": {
                "label": "SWP",
                "color": "blue"
              },
              "th": 786,
              "ck": 743.2,
              "kh": 769.5,
              "pct_ck": {
                "direction": "up",
                "label": "+5,8%",
                "color": "green"
              },
              "pct_kh": {
                "direction": "up",
                "label": "+2,1%",
                "color": "green"
              },
              "unit": "VND/ghế/km"
            },
            "depth": 0
          },
          {
            "id": "australia",
            "cells": {
              "level": {
                "label": "Australia",
                "color": "yellow"
              },
              "th": 635.9,
              "ck": 605.8,
              "kh": 631.3,
              "pct_ck": {
                "direction": "up",
                "label": "+5,0%",
                "color": "green"
              },
              "pct_kh": {
                "direction": "up",
                "label": "+0,7%",
                "color": "green"
              },
              "unit": "VND/ghế/km"
            },
            "depth": 1
          },
          {
            "id": "sea",
            "cells": {
              "level": {
                "label": "SEA",
                "color": "green"
              },
              "th": 707.4,
              "ck": 671.4,
              "kh": 697.4,
              "pct_ck": {
                "direction": "up",
                "label": "+5,4%",
                "color": "green"
              },
              "pct_kh": {
                "direction": "up",
                "label": "+1,4%",
                "color": "green"
              },
              "unit": "VND/ghế/km"
            },
            "depth": 0
          },
          {
            "id": "thailand",
            "cells": {
              "level": {
                "label": "Thailand",
                "color": "default"
              },
              "th": 0.1,
              "ck": 0.1,
              "kh": 0.1,
              "pct_ck": {
                "direction": "up",
                "label": "+0,0%",
                "color": "green"
              },
              "pct_kh": {
                "direction": "up",
                "label": "+0,0%",
                "color": "green"
              },
              "unit": "VND/ghế/km"
            },
            "depth": 1
          },
          {
            "id": "eur",
            "cells": {
              "level": {
                "label": "EUR",
                "color": "default"
              },
              "th": 632.4,
              "ck": 602.6,
              "kh": 627.8,
              "pct_ck": {
                "direction": "up",
                "label": "+4,9%",
                "color": "green"
              },
              "pct_kh": {
                "direction": "up",
                "label": "+0,7%",
                "color": "green"
              },
              "unit": "VND/ghế/km"
            },
            "depth": 0
          },
          {
            "id": "france",
            "cells": {
              "level": {
                "label": "France",
                "color": "blue"
              },
              "th": 584.2,
              "ck": 558.6,
              "kh": 582.4,
              "pct_ck": {
                "direction": "up",
                "label": "+4,6%",
                "color": "green"
              },
              "pct_kh": {
                "direction": "up",
                "label": "+0,3%",
                "color": "green"
              },
              "unit": "VND/ghế/km"
            },
            "depth": 1
          },
          {
            "id": "germany",
            "cells": {
              "level": {
                "label": "Germany",
                "color": "green"
              },
              "th": 534.2,
              "ck": 511.5,
              "kh": 532.8,
              "pct_ck": {
                "direction": "up",
                "label": "+4,4%",
                "color": "green"
              },
              "pct_kh": {
                "direction": "up",
                "label": "+0,3%",
                "color": "green"
              },
              "unit": "VND/ghế/km"
            },
            "depth": 1
          },
          {
            "id": "sas",
            "cells": {
              "level": {
                "label": "SAS",
                "color": "yellow"
              },
              "th": 560.4,
              "ck": 535.9,
              "kh": 559.1,
              "pct_ck": {
                "direction": "up",
                "label": "+4,6%",
                "color": "green"
              },
              "pct_kh": {
                "direction": "up",
                "label": "+0,2%",
                "color": "green"
              },
              "unit": "VND/ghế/km"
            },
            "depth": 0
          },
          {
            "id": "hansgn",
            "cells": {
              "level": {
                "label": "HANSGN",
                "color": "blue"
              },
              "th": 1101.2,
              "ck": 1048.9,
              "kh": 1087.9,
              "pct_ck": {
                "direction": "up",
                "label": "+5,0%",
                "color": "green"
              },
              "pct_kh": {
                "direction": "up",
                "label": "+1,2%",
                "color": "green"
              },
              "unit": "VND/ghế/km"
            },
            "depth": 0
          },
          {
            "id": "vietnam",
            "cells": {
              "level": {
                "label": "Vietnam",
                "color": "blue"
              },
              "th": 810.4,
              "ck": 764.2,
              "kh": 788.4,
              "pct_ck": {
                "direction": "up",
                "label": "+6,0%",
                "color": "green"
              },
              "pct_kh": {
                "direction": "up",
                "label": "+2,8%",
                "color": "green"
              },
              "unit": "VND/ghế/km"
            },
            "depth": 1
          },
          {
            "id": "handad",
            "cells": {
              "level": {
                "label": "HANDAD",
                "color": "green"
              },
              "th": 1030.5,
              "ck": 981.2,
              "kh": 1015.9,
              "pct_ck": {
                "direction": "up",
                "label": "+5,0%",
                "color": "green"
              },
              "pct_kh": {
                "direction": "up",
                "label": "+1,4%",
                "color": "green"
              },
              "unit": "VND/ghế/km"
            },
            "depth": 0
          },
          {
            "id": "vietnam",
            "cells": {
              "level": {
                "label": "Vietnam",
                "color": "blue"
              },
              "th": 810.4,
              "ck": 764.2,
              "kh": 788.4,
              "pct_ck": {
                "direction": "up",
                "label": "+6,0%",
                "color": "green"
              },
              "pct_kh": {
                "direction": "up",
                "label": "+2,8%",
                "color": "green"
              },
              "unit": "VND/ghế/km"
            },
            "depth": 1
          },
          {
            "id": "sgndad",
            "cells": {
              "level": {
                "label": "SGNDAD",
                "color": "default"
              },
              "th": 957.9,
              "ck": 910.3,
              "kh": 940.1,
              "pct_ck": {
                "direction": "up",
                "label": "+5,2%",
                "color": "green"
              },
              "pct_kh": {
                "direction": "up",
                "label": "+1,9%",
                "color": "green"
              },
              "unit": "VND/ghế/km"
            },
            "depth": 0
          },
          {
            "id": "vietnam",
            "cells": {
              "level": {
                "label": "Vietnam",
                "color": "blue"
              },
              "th": 810.4,
              "ck": 764.2,
              "kh": 788.4,
              "pct_ck": {
                "direction": "up",
                "label": "+6,0%",
                "color": "green"
              },
              "pct_kh": {
                "direction": "up",
                "label": "+2,8%",
                "color": "green"
              },
              "unit": "VND/ghế/km"
            },
            "depth": 1
          },
          {
            "id": "trục_lẻ",
            "cells": {
              "level": {
                "label": "Trục lẻ",
                "color": "yellow"
              },
              "th": 881.9,
              "ck": 835.8,
              "kh": 860.7,
              "pct_ck": {
                "direction": "up",
                "label": "+5,5%",
                "color": "green"
              },
              "pct_kh": {
                "direction": "up",
                "label": "+2,5%",
                "color": "green"
              },
              "unit": "VND/ghế/km"
            },
            "depth": 0
          },
          {
            "id": "vietnam",
            "cells": {
              "level": {
                "label": "Vietnam",
                "color": "blue"
              },
              "th": 810.4,
              "ck": 764.2,
              "kh": 788.4,
              "pct_ck": {
                "direction": "up",
                "label": "+6,0%",
                "color": "green"
              },
              "pct_kh": {
                "direction": "up",
                "label": "+2,8%",
                "color": "green"
              },
              "unit": "VND/ghế/km"
            },
            "depth": 1
          },
          {
            "id": "du_lịch",
            "cells": {
              "level": {
                "label": "Du lịch",
                "color": "blue"
              },
              "th": 802.3,
              "ck": 758,
              "kh": 778.4,
              "pct_ck": {
                "direction": "up",
                "label": "+5,8%",
                "color": "green"
              },
              "pct_kh": {
                "direction": "up",
                "label": "+3,1%",
                "color": "green"
              },
              "unit": "VND/ghế/km"
            },
            "depth": 0
          },
          {
            "id": "vietnam",
            "cells": {
              "level": {
                "label": "Vietnam",
                "color": "blue"
              },
              "th": 810.4,
              "ck": 764.2,
              "kh": 788.4,
              "pct_ck": {
                "direction": "up",
                "label": "+6,0%",
                "color": "green"
              },
              "pct_kh": {
                "direction": "up",
                "label": "+2,8%",
                "color": "green"
              },
              "unit": "VND/ghế/km"
            },
            "depth": 1
          },
          {
            "id": "dịa_phương",
            "cells": {
              "level": {
                "label": "Địa phương",
                "color": "green"
              },
              "th": 0.1,
              "ck": 0.1,
              "kh": 0.1,
              "pct_ck": {
                "direction": "up",
                "label": "+0,0%",
                "color": "green"
              },
              "pct_kh": {
                "direction": "up",
                "label": "+0,0%",
                "color": "green"
              },
              "unit": "VND/ghế/km"
            },
            "depth": 0
          },
          {
            "id": "vietnam",
            "cells": {
              "level": {
                "label": "Vietnam",
                "color": "blue"
              },
              "th": 810.4,
              "ck": 764.2,
              "kh": 788.4,
              "pct_ck": {
                "direction": "up",
                "label": "+6,0%",
                "color": "green"
              },
              "pct_kh": {
                "direction": "up",
                "label": "+2,8%",
                "color": "green"
              },
              "unit": "VND/ghế/km"
            },
            "depth": 1
          }
        ],
        "maxHeight": 385,
        "minHeight": 385
      },
      "aiInsight": {
        "text": "CASK toàn mạng cho thấy áp lực chi phí theo mức; cần kiểm soát chi phí đơn vị ghế.km.",
        "severity": "warn",
        "status": 1
      },
      "title": "Chi tiết CASK theo Country"
    },
    {
      "label": "Route",
      "table": {
        "columns": [
          {
            "id": "level",
            "label": "TÊN MỨC",
            "type": "chip",
            "align": "left"
          },
          {
            "id": "th",
            "label": "TH",
            "type": "number",
            "align": "right",
            "decimals": 1
          },
          {
            "id": "ck",
            "label": "CK",
            "type": "number",
            "align": "right",
            "decimals": 1
          },
          {
            "id": "kh",
            "label": "KH",
            "type": "number",
            "align": "right",
            "decimals": 1
          },
          {
            "id": "pct_ck",
            "label": "% CK",
            "type": "trend",
            "align": "right"
          },
          {
            "id": "pct_kh",
            "label": "% KH",
            "type": "trend",
            "align": "right"
          },
          {
            "id": "unit",
            "label": "Đơn vị",
            "type": "text",
            "align": "left"
          }
        ],
        "rows": [
          {
            "id": "clmv",
            "cells": {
              "level": {
                "label": "CLMV",
                "color": "blue"
              },
              "th": 1122.1,
              "ck": 1059.8,
              "kh": 1089.9,
              "pct_ck": {
                "direction": "up",
                "label": "+5,9%",
                "color": "green"
              },
              "pct_kh": {
                "direction": "up",
                "label": "+3,0%",
                "color": "green"
              },
              "unit": "VND/ghế/km"
            },
            "depth": 0
          },
          {
            "id": "vietnam",
            "cells": {
              "level": {
                "label": "Vietnam",
                "color": "blue"
              },
              "th": 810.4,
              "ck": 764.2,
              "kh": 788.4,
              "pct_ck": {
                "direction": "up",
                "label": "+6,0%",
                "color": "green"
              },
              "pct_kh": {
                "direction": "up",
                "label": "+2,8%",
                "color": "green"
              },
              "unit": "VND/ghế/km"
            },
            "depth": 1
          },
          {
            "id": "nea",
            "cells": {
              "level": {
                "label": "NEA",
                "color": "green"
              },
              "th": 1037.9,
              "ck": 978.7,
              "kh": 1006.4,
              "pct_ck": {
                "direction": "up",
                "label": "+6,0%",
                "color": "green"
              },
              "pct_kh": {
                "direction": "up",
                "label": "+3,1%",
                "color": "green"
              },
              "unit": "VND/ghế/km"
            },
            "depth": 0
          },
          {
            "id": "korea",
            "cells": {
              "level": {
                "label": "Korea",
                "color": "green"
              },
              "th": 748.7,
              "ck": 708,
              "kh": 733,
              "pct_ck": {
                "direction": "up",
                "label": "+5,7%",
                "color": "green"
              },
              "pct_kh": {
                "direction": "up",
                "label": "+2,1%",
                "color": "green"
              },
              "unit": "VND/ghế/km"
            },
            "depth": 1
          },
          {
            "id": "japan",
            "cells": {
              "level": {
                "label": "Japan",
                "color": "default"
              },
              "th": 690.4,
              "ck": 655.3,
              "kh": 680.8,
              "pct_ck": {
                "direction": "up",
                "label": "+5,4%",
                "color": "green"
              },
              "pct_kh": {
                "direction": "up",
                "label": "+1,4%",
                "color": "green"
              },
              "unit": "VND/ghế/km"
            },
            "depth": 1
          },
          {
            "id": "mid",
            "cells": {
              "level": {
                "label": "MID",
                "color": "default"
              },
              "th": 952.6,
              "ck": 898,
              "kh": 924.2,
              "pct_ck": {
                "direction": "up",
                "label": "+6,1%",
                "color": "green"
              },
              "pct_kh": {
                "direction": "up",
                "label": "+3,1%",
                "color": "green"
              },
              "unit": "VND/ghế/km"
            },
            "depth": 0
          },
          {
            "id": "noa",
            "cells": {
              "level": {
                "label": "NOA",
                "color": "yellow"
              },
              "th": 868.1,
              "ck": 819,
              "kh": 845,
              "pct_ck": {
                "direction": "up",
                "label": "+6,0%",
                "color": "green"
              },
              "pct_kh": {
                "direction": "up",
                "label": "+2,7%",
                "color": "green"
              },
              "unit": "VND/ghế/km"
            },
            "depth": 0
          },
          {
            "id": "swp",
            "cells": {
              "level": {
                "label": "SWP",
                "color": "blue"
              },
              "th": 786,
              "ck": 743.2,
              "kh": 769.5,
              "pct_ck": {
                "direction": "up",
                "label": "+5,8%",
                "color": "green"
              },
              "pct_kh": {
                "direction": "up",
                "label": "+2,1%",
                "color": "green"
              },
              "unit": "VND/ghế/km"
            },
            "depth": 0
          },
          {
            "id": "australia",
            "cells": {
              "level": {
                "label": "Australia",
                "color": "yellow"
              },
              "th": 635.9,
              "ck": 605.8,
              "kh": 631.3,
              "pct_ck": {
                "direction": "up",
                "label": "+5,0%",
                "color": "green"
              },
              "pct_kh": {
                "direction": "up",
                "label": "+0,7%",
                "color": "green"
              },
              "unit": "VND/ghế/km"
            },
            "depth": 1
          },
          {
            "id": "sea",
            "cells": {
              "level": {
                "label": "SEA",
                "color": "green"
              },
              "th": 707.4,
              "ck": 671.4,
              "kh": 697.4,
              "pct_ck": {
                "direction": "up",
                "label": "+5,4%",
                "color": "green"
              },
              "pct_kh": {
                "direction": "up",
                "label": "+1,4%",
                "color": "green"
              },
              "unit": "VND/ghế/km"
            },
            "depth": 0
          },
          {
            "id": "thailand",
            "cells": {
              "level": {
                "label": "Thailand",
                "color": "default"
              },
              "th": 0.1,
              "ck": 0.1,
              "kh": 0.1,
              "pct_ck": {
                "direction": "up",
                "label": "+0,0%",
                "color": "green"
              },
              "pct_kh": {
                "direction": "up",
                "label": "+0,0%",
                "color": "green"
              },
              "unit": "VND/ghế/km"
            },
            "depth": 1
          },
          {
            "id": "eur",
            "cells": {
              "level": {
                "label": "EUR",
                "color": "default"
              },
              "th": 632.4,
              "ck": 602.6,
              "kh": 627.8,
              "pct_ck": {
                "direction": "up",
                "label": "+4,9%",
                "color": "green"
              },
              "pct_kh": {
                "direction": "up",
                "label": "+0,7%",
                "color": "green"
              },
              "unit": "VND/ghế/km"
            },
            "depth": 0
          },
          {
            "id": "france",
            "cells": {
              "level": {
                "label": "France",
                "color": "blue"
              },
              "th": 584.2,
              "ck": 558.6,
              "kh": 582.4,
              "pct_ck": {
                "direction": "up",
                "label": "+4,6%",
                "color": "green"
              },
              "pct_kh": {
                "direction": "up",
                "label": "+0,3%",
                "color": "green"
              },
              "unit": "VND/ghế/km"
            },
            "depth": 1
          },
          {
            "id": "germany",
            "cells": {
              "level": {
                "label": "Germany",
                "color": "green"
              },
              "th": 534.2,
              "ck": 511.5,
              "kh": 532.8,
              "pct_ck": {
                "direction": "up",
                "label": "+4,4%",
                "color": "green"
              },
              "pct_kh": {
                "direction": "up",
                "label": "+0,3%",
                "color": "green"
              },
              "unit": "VND/ghế/km"
            },
            "depth": 1
          },
          {
            "id": "sas",
            "cells": {
              "level": {
                "label": "SAS",
                "color": "yellow"
              },
              "th": 560.4,
              "ck": 535.9,
              "kh": 559.1,
              "pct_ck": {
                "direction": "up",
                "label": "+4,6%",
                "color": "green"
              },
              "pct_kh": {
                "direction": "up",
                "label": "+0,2%",
                "color": "green"
              },
              "unit": "VND/ghế/km"
            },
            "depth": 0
          },
          {
            "id": "hansgn",
            "cells": {
              "level": {
                "label": "HANSGN",
                "color": "blue"
              },
              "th": 1101.2,
              "ck": 1048.9,
              "kh": 1087.9,
              "pct_ck": {
                "direction": "up",
                "label": "+5,0%",
                "color": "green"
              },
              "pct_kh": {
                "direction": "up",
                "label": "+1,2%",
                "color": "green"
              },
              "unit": "VND/ghế/km"
            },
            "depth": 0
          },
          {
            "id": "vietnam",
            "cells": {
              "level": {
                "label": "Vietnam",
                "color": "blue"
              },
              "th": 810.4,
              "ck": 764.2,
              "kh": 788.4,
              "pct_ck": {
                "direction": "up",
                "label": "+6,0%",
                "color": "green"
              },
              "pct_kh": {
                "direction": "up",
                "label": "+2,8%",
                "color": "green"
              },
              "unit": "VND/ghế/km"
            },
            "depth": 1
          },
          {
            "id": "han_sgn",
            "cells": {
              "level": {
                "label": "HAN-SGN",
                "color": "blue"
              },
              "th": 212.8,
              "ck": 204.9,
              "kh": 216.9,
              "pct_ck": {
                "direction": "up",
                "label": "+3,9%",
                "color": "green"
              },
              "pct_kh": {
                "direction": "down",
                "label": "-1,9%",
                "color": "red"
              },
              "unit": "VND/ghế/km"
            },
            "depth": 2
          },
          {
            "id": "handad",
            "cells": {
              "level": {
                "label": "HANDAD",
                "color": "green"
              },
              "th": 1030.5,
              "ck": 981.2,
              "kh": 1015.9,
              "pct_ck": {
                "direction": "up",
                "label": "+5,0%",
                "color": "green"
              },
              "pct_kh": {
                "direction": "up",
                "label": "+1,4%",
                "color": "green"
              },
              "unit": "VND/ghế/km"
            },
            "depth": 0
          },
          {
            "id": "vietnam",
            "cells": {
              "level": {
                "label": "Vietnam",
                "color": "blue"
              },
              "th": 810.4,
              "ck": 764.2,
              "kh": 788.4,
              "pct_ck": {
                "direction": "up",
                "label": "+6,0%",
                "color": "green"
              },
              "pct_kh": {
                "direction": "up",
                "label": "+2,8%",
                "color": "green"
              },
              "unit": "VND/ghế/km"
            },
            "depth": 1
          },
          {
            "id": "han_dad",
            "cells": {
              "level": {
                "label": "HAN-DAD",
                "color": "default"
              },
              "th": 194.4,
              "ck": 189.5,
              "kh": 199.9,
              "pct_ck": {
                "direction": "up",
                "label": "+2,6%",
                "color": "green"
              },
              "pct_kh": {
                "direction": "down",
                "label": "-2,8%",
                "color": "red"
              },
              "unit": "VND/ghế/km"
            },
            "depth": 2
          },
          {
            "id": "sgndad",
            "cells": {
              "level": {
                "label": "SGNDAD",
                "color": "default"
              },
              "th": 957.9,
              "ck": 910.3,
              "kh": 940.1,
              "pct_ck": {
                "direction": "up",
                "label": "+5,2%",
                "color": "green"
              },
              "pct_kh": {
                "direction": "up",
                "label": "+1,9%",
                "color": "green"
              },
              "unit": "VND/ghế/km"
            },
            "depth": 0
          },
          {
            "id": "vietnam",
            "cells": {
              "level": {
                "label": "Vietnam",
                "color": "blue"
              },
              "th": 810.4,
              "ck": 764.2,
              "kh": 788.4,
              "pct_ck": {
                "direction": "up",
                "label": "+6,0%",
                "color": "green"
              },
              "pct_kh": {
                "direction": "up",
                "label": "+2,8%",
                "color": "green"
              },
              "unit": "VND/ghế/km"
            },
            "depth": 1
          },
          {
            "id": "trục_lẻ",
            "cells": {
              "level": {
                "label": "Trục lẻ",
                "color": "yellow"
              },
              "th": 881.9,
              "ck": 835.8,
              "kh": 860.7,
              "pct_ck": {
                "direction": "up",
                "label": "+5,5%",
                "color": "green"
              },
              "pct_kh": {
                "direction": "up",
                "label": "+2,5%",
                "color": "green"
              },
              "unit": "VND/ghế/km"
            },
            "depth": 0
          },
          {
            "id": "vietnam",
            "cells": {
              "level": {
                "label": "Vietnam",
                "color": "blue"
              },
              "th": 810.4,
              "ck": 764.2,
              "kh": 788.4,
              "pct_ck": {
                "direction": "up",
                "label": "+6,0%",
                "color": "green"
              },
              "pct_kh": {
                "direction": "up",
                "label": "+2,8%",
                "color": "green"
              },
              "unit": "VND/ghế/km"
            },
            "depth": 1
          },
          {
            "id": "hph_sgn",
            "cells": {
              "level": {
                "label": "HPH-SGN",
                "color": "green"
              },
              "th": 202.7,
              "ck": 196.9,
              "kh": 208.8,
              "pct_ck": {
                "direction": "up",
                "label": "+2,9%",
                "color": "green"
              },
              "pct_kh": {
                "direction": "down",
                "label": "-2,9%",
                "color": "red"
              },
              "unit": "VND/ghế/km"
            },
            "depth": 2
          },
          {
            "id": "thd_sgn",
            "cells": {
              "level": {
                "label": "THD-SGN",
                "color": "yellow"
              },
              "th": 185.9,
              "ck": 180.6,
              "kh": 188.5,
              "pct_ck": {
                "direction": "up",
                "label": "+2,9%",
                "color": "green"
              },
              "pct_kh": {
                "direction": "down",
                "label": "-1,4%",
                "color": "red"
              },
              "unit": "VND/ghế/km"
            },
            "depth": 2
          },
          {
            "id": "han_vca",
            "cells": {
              "level": {
                "label": "HAN-VCA",
                "color": "blue"
              },
              "th": 175.2,
              "ck": 168.4,
              "kh": 173.3,
              "pct_ck": {
                "direction": "up",
                "label": "+4,0%",
                "color": "green"
              },
              "pct_kh": {
                "direction": "up",
                "label": "+1,1%",
                "color": "green"
              },
              "unit": "VND/ghế/km"
            },
            "depth": 2
          },
          {
            "id": "han_cxr",
            "cells": {
              "level": {
                "label": "HAN-CXR",
                "color": "green"
              },
              "th": 161.2,
              "ck": 152.6,
              "kh": 154.8,
              "pct_ck": {
                "direction": "up",
                "label": "+5,6%",
                "color": "green"
              },
              "pct_kh": {
                "direction": "up",
                "label": "+4,1%",
                "color": "green"
              },
              "unit": "VND/ghế/km"
            },
            "depth": 2
          },
          {
            "id": "vii_sgn",
            "cells": {
              "level": {
                "label": "VII-SGN",
                "color": "default"
              },
              "th": 143.7,
              "ck": 133.6,
              "kh": 133.3,
              "pct_ck": {
                "direction": "up",
                "label": "+7,6%",
                "color": "green"
              },
              "pct_kh": {
                "direction": "up",
                "label": "+7,8%",
                "color": "green"
              },
              "unit": "VND/ghế/km"
            },
            "depth": 2
          },
          {
            "id": "han_dli",
            "cells": {
              "level": {
                "label": "HAN-DLI",
                "color": "yellow"
              },
              "th": 123.1,
              "ck": 112.1,
              "kh": 110.6,
              "pct_ck": {
                "direction": "up",
                "label": "+9,8%",
                "color": "green"
              },
              "pct_kh": {
                "direction": "up",
                "label": "+11,3%",
                "color": "green"
              },
              "unit": "VND/ghế/km"
            },
            "depth": 2
          },
          {
            "id": "han_bmv",
            "cells": {
              "level": {
                "label": "HAN-BMV",
                "color": "blue"
              },
              "th": 223.9,
              "ck": 207,
              "kh": 209.4,
              "pct_ck": {
                "direction": "up",
                "label": "+8,2%",
                "color": "green"
              },
              "pct_kh": {
                "direction": "up",
                "label": "+6,9%",
                "color": "green"
              },
              "unit": "VND/ghế/km"
            },
            "depth": 2
          },
          {
            "id": "han_pqc",
            "cells": {
              "level": {
                "label": "HAN-PQC",
                "color": "green"
              },
              "th": 200.7,
              "ck": 185.5,
              "kh": 189,
              "pct_ck": {
                "direction": "up",
                "label": "+8,2%",
                "color": "green"
              },
              "pct_kh": {
                "direction": "up",
                "label": "+6,2%",
                "color": "green"
              },
              "unit": "VND/ghế/km"
            },
            "depth": 2
          },
          {
            "id": "han_pxu",
            "cells": {
              "level": {
                "label": "HAN-PXU",
                "color": "default"
              },
              "th": 179,
              "ck": 166.5,
              "kh": 172,
              "pct_ck": {
                "direction": "up",
                "label": "+7,5%",
                "color": "green"
              },
              "pct_kh": {
                "direction": "up",
                "label": "+4,1%",
                "color": "green"
              },
              "unit": "VND/ghế/km"
            },
            "depth": 2
          },
          {
            "id": "han_hui",
            "cells": {
              "level": {
                "label": "HAN-HUI",
                "color": "yellow"
              },
              "th": 160.5,
              "ck": 151.4,
              "kh": 158.9,
              "pct_ck": {
                "direction": "up",
                "label": "+6,0%",
                "color": "green"
              },
              "pct_kh": {
                "direction": "up",
                "label": "+1,0%",
                "color": "green"
              },
              "unit": "VND/ghế/km"
            },
            "depth": 2
          },
          {
            "id": "han_tbb",
            "cells": {
              "level": {
                "label": "HAN-TBB",
                "color": "blue"
              },
              "th": 145.4,
              "ck": 139.8,
              "kh": 148.9,
              "pct_ck": {
                "direction": "up",
                "label": "+4,0%",
                "color": "green"
              },
              "pct_kh": {
                "direction": "down",
                "label": "-2,4%",
                "color": "red"
              },
              "unit": "VND/ghế/km"
            },
            "depth": 2
          },
          {
            "id": "han_uih",
            "cells": {
              "level": {
                "label": "HAN-UIH",
                "color": "green"
              },
              "th": 134,
              "ck": 131.1,
              "kh": 140.8,
              "pct_ck": {
                "direction": "up",
                "label": "+2,2%",
                "color": "green"
              },
              "pct_kh": {
                "direction": "down",
                "label": "-4,8%",
                "color": "red"
              },
              "unit": "VND/ghế/km"
            },
            "depth": 2
          },
          {
            "id": "han_din",
            "cells": {
              "level": {
                "label": "HAN-DIN",
                "color": "default"
              },
              "th": 124.8,
              "ck": 123.5,
              "kh": 132.5,
              "pct_ck": {
                "direction": "up",
                "label": "+1,1%",
                "color": "green"
              },
              "pct_kh": {
                "direction": "down",
                "label": "-5,8%",
                "color": "red"
              },
              "unit": "VND/ghế/km"
            },
            "depth": 2
          },
          {
            "id": "han_vcl",
            "cells": {
              "level": {
                "label": "HAN-VCL",
                "color": "yellow"
              },
              "th": 0.1,
              "ck": 0.1,
              "kh": 0.1,
              "pct_ck": {
                "direction": "up",
                "label": "+0,0%",
                "color": "green"
              },
              "pct_kh": {
                "direction": "up",
                "label": "+0,0%",
                "color": "green"
              },
              "unit": "VND/ghế/km"
            },
            "depth": 2
          },
          {
            "id": "du_lịch",
            "cells": {
              "level": {
                "label": "Du lịch",
                "color": "blue"
              },
              "th": 802.3,
              "ck": 758,
              "kh": 778.4,
              "pct_ck": {
                "direction": "up",
                "label": "+5,8%",
                "color": "green"
              },
              "pct_kh": {
                "direction": "up",
                "label": "+3,1%",
                "color": "green"
              },
              "unit": "VND/ghế/km"
            },
            "depth": 0
          },
          {
            "id": "vietnam",
            "cells": {
              "level": {
                "label": "Vietnam",
                "color": "blue"
              },
              "th": 810.4,
              "ck": 764.2,
              "kh": 788.4,
              "pct_ck": {
                "direction": "up",
                "label": "+6,0%",
                "color": "green"
              },
              "pct_kh": {
                "direction": "up",
                "label": "+2,8%",
                "color": "green"
              },
              "unit": "VND/ghế/km"
            },
            "depth": 1
          },
          {
            "id": "dịa_phương",
            "cells": {
              "level": {
                "label": "Địa phương",
                "color": "green"
              },
              "th": 0.1,
              "ck": 0.1,
              "kh": 0.1,
              "pct_ck": {
                "direction": "up",
                "label": "+0,0%",
                "color": "green"
              },
              "pct_kh": {
                "direction": "up",
                "label": "+0,0%",
                "color": "green"
              },
              "unit": "VND/ghế/km"
            },
            "depth": 0
          },
          {
            "id": "vietnam",
            "cells": {
              "level": {
                "label": "Vietnam",
                "color": "blue"
              },
              "th": 810.4,
              "ck": 764.2,
              "kh": 788.4,
              "pct_ck": {
                "direction": "up",
                "label": "+6,0%",
                "color": "green"
              },
              "pct_kh": {
                "direction": "up",
                "label": "+2,8%",
                "color": "green"
              },
              "unit": "VND/ghế/km"
            },
            "depth": 1
          }
        ],
        "maxHeight": 385,
        "minHeight": 385
      },
      "aiInsight": {
        "text": "CASK toàn mạng cho thấy áp lực chi phí theo mức; cần kiểm soát chi phí đơn vị ghế.km.",
        "severity": "warn",
        "status": 1
      },
      "title": "Chi tiết CASK theo Route"
    }
  ]
}
