{
  "autoChart": {
    "chartType": "auto",
    "dataset": {
      "columns": [
        {
          "id": "quarter",
          "type": "string"
        },
        {
          "id": "th",
          "type": "number",
          "label": "2026",
          "color": "#006D88"
        },
        {
          "id": "ck",
          "type": "number",
          "label": "2025",
          "color": "#9AA0A6"
        },
        {
          "id": "db",
          "type": "number",
          "label": "KH 2026",
          "color": "#D3AC2B"
        },
        {
          "id": "uth",
          "type": "number",
          "label": "Dự báo",
          "color": "#006D88"
        }
      ],
      "rows": [
        [
          "Q1",
          186.3,
          196.29999999999998,
          229.0,
          null
        ],
        [
          "Q2",
          184.8,
          175.0,
          205.1,
          null
        ],
        [
          "Q3",
          55.2,
          155.3,
          186.7,
          104.4
        ],
        [
          "Q4",
          null,
          134.7,
          172.60000000000002,
          147.6
        ]
      ]
    },
    "views": [
      {
        "id": "main",
        "chartType": "auto",
        "xField": "quarter",
        "series": [
          {
            "field": "th",
            "chartType": "line"
          },
          {
            "field": "ck",
            "chartType": "line"
          },
          {
            "field": "db",
            "chartType": "line",
            "lineStyle": "dashed"
          },
          {
            "field": "uth",
            "chartType": "bar"
          }
        ]
      }
    ]
  },
  "metadata": {
    "chartType": "line",
    "pattern": "fluctuation",
    "unit": "VND/ghế.km",
    "description": "RASK - Doanh thu trên ghế km - nội địa",
    "forecastStartIndex": 3
  }
}