{
  "autoChart": {
    "chartType": "auto",
    "dataset": {
      "columns": [
        {
          "id": "month",
          "type": "string"
        },
        {
          "id": "ck",
          "type": "number",
          "label": "Cùng kỳ",
          "color": "#9AA0A6"
        },
        {
          "id": "db",
          "type": "number",
          "label": "Kế hoạch",
          "color": "#D3AC2B"
        },
        {
          "id": "th",
          "type": "number",
          "label": "Thực hiện",
          "color": "#006D88"
        },
        {
          "id": "uth",
          "type": "number",
          "label": "Dự báo",
          "color": "#006D88"
        }
      ],
      "rows": [
        [
          "T1",
          86.6,
          95.6,
          79,
          null
        ],
        [
          "T2",
          86.2,
          89.7,
          82.3,
          null
        ],
        [
          "T3",
          81.9,
          94.2,
          75.5,
          null
        ],
        [
          "T4",
          83,
          104.7,
          79.3,
          null
        ],
        [
          "T5",
          84.5,
          93.2,
          78,
          null
        ],
        [
          "T6",
          90.3,
          100.3,
          84.8,
          null
        ],
        [
          "T7",
          91.4,
          93.6,
          85.4,
          null
        ],
        [
          "T8",
          75.8,
          83.1,
          null,
          70.6
        ],
        [
          "T9",
          74.4,
          85.9,
          null,
          73.0
        ],
        [
          "T10",
          82.5,
          90.2,
          null,
          76.7
        ],
        [
          "T11",
          83.3,
          85.8,
          null,
          72.9
        ],
        [
          "T12",
          87.8,
          85.4,
          null,
          72.6
        ]
      ]
    },
    "views": [
      {
        "id": "main",
        "chartType": "auto",
        "xField": "month",
        "series": [
          {
            "field": "ck",
            "chartType": "line"
          },
          {
            "field": "db",
            "chartType": "line"
          },
          {
            "field": "th",
            "chartType": "line"
          },
          {
            "field": "uth",
            "chartType": "bar"
          }
        ]
      }
    ]
  },
  "metadata": {
    "chartType": "line",
    "pattern": "upWave",
    "description": "int int nea",
    "forecastStartIndex": 8
  }
}
