{
  "autoChart": {
    "chartType": "auto",
    "dataset": {
      "columns": [
        {
          "id": "month",
          "type": "string"
        },
        {
          "id": "ck",
          "type": "number",
          "label": "Cùng kỳ",
          "color": "#ec4899"
        },
        {
          "id": "db",
          "type": "number",
          "label": "Dự báo",
          "color": "#d0d1d3"
        },
        {
          "id": "th",
          "type": "number",
          "label": "Thực hiện",
          "color": "#2962a0"
        }
      ],
      "rows": [
        [
          "T1",
          53,
          67,
          51
        ],
        [
          "T2",
          52,
          66,
          51
        ],
        [
          "T3",
          51,
          63,
          50
        ],
        [
          "T4",
          50,
          64,
          48
        ],
        [
          "T5",
          49,
          62,
          47
        ],
        [
          "T6",
          47,
          60,
          46
        ],
        [
          "T7",
          46,
          59,
          44
        ],
        [
          "T8",
          43,
          60,
          null
        ],
        [
          "T9",
          43,
          58,
          null
        ],
        [
          "T10",
          40,
          57,
          null
        ],
        [
          "T11",
          40,
          57,
          null
        ],
        [
          "T12",
          37,
          55,
          null
        ]
      ]
    },
    "views": [
      {
        "id": "main",
        "chartType": "auto",
        "xField": "month",
        "series": [
          {
            "field": "ck",
            "chartType": "line"
          },
          {
            "field": "db",
            "chartType": "line"
          },
          {
            "field": "th",
            "chartType": "line"
          }
        ]
      }
    ]
  }
}